{
    "version": "7",
    "dialect": "postgresql",
    "entries": [
        {
            "idx": 0,
            "version": "7",
            "when": 1768393496861,
            "tag": "0000_swift_luckman",
            "breakpoints": true
        },
        {
            "idx": 1,
            "version": "7",
            "when": 1769775615751,
            "tag": "0001_ancient_the_fury",
            "breakpoints": true
        },
        {
            "idx": 2,
            "version": "7",
            "when": 1769946457530,
            "tag": "0002_dark_the_twelve",
            "breakpoints": true
        },
        {
            "idx": 3,
            "version": "7",
            "when": 1770121923216,
            "tag": "0003_absurd_shadowcat",
            "breakpoints": true
        }
    ]
}
